{
  "project_info": {
    "project_number": "83064937407",
    "project_id": "myauthentication-534e5",
    "storage_bucket": "myauthentication-534e5.appspot.com"
  },
  "client": [
    {
      "client_info": {
        "mobilesdk_app_id": "1:83064937407:android:908f2196c3fb1938a49f0a",
        "android_client_info": {
          "package_name": "com.example.mobile_number_auth"
        }
      },
      "oauth_client": [
        {
          "client_id": "83064937407-g61a1cne1ca4cbkc8pjt6vo3lid2c3ej.apps.googleusercontent.com",
          "client_type": 1,
          "android_info": {
            "package_name": "com.example.mobile_number_auth",
            "certificate_hash": "81177167e4c37b850ff26461dd6cf68da3e3d48a"
          }
        },
        {
          "client_id": "83064937407-lcqn8vdcg9j6akkbnn61622d2mi6bjj2.apps.googleusercontent.com",
          "client_type": 3
        }
      ],
      "api_key": [
        {
          "current_key": "AIzaSyDTL2SYPDxFfTb6nanTUja_KQpx-DhkRs8"
        }
      ],
      "services": {
        "appinvite_service": {
          "other_platform_oauth_client": [
            {
              "client_id": "83064937407-lcqn8vdcg9j6akkbnn61622d2mi6bjj2.apps.googleusercontent.com",
              "client_type": 3
            },
            {
              "client_id": "83064937407-p14mrgjpuppat9euqcft5aekpaana3e9.apps.googleusercontent.com",
              "client_type": 2,
              "ios_info": {
                "bundle_id": "com.example.mobileNumberAuth"
              }
            }
          ]
        }
      }
    }
  ],
  "configuration_version": "1"
}